funcrunner/__init__.py
funcrunner/app.py
funcrunner/exceptions.py
funcrunner/health.py
funcrunner/models.py
funcrunner/tool_definitions.py
funcrunner-1.1.13.dist-info/METADATA
funcrunner-1.1.13.dist-info/WHEEL
funcrunner-1.1.13.dist-info/RECORD
