Metadata-Version: 2.1
Name: funcrunner
Version: 1.1.13
Summary: A managed function calling framework for OpenAI Assistants.
Home-page: https://funcrunner.com
License: Proprietary
Author: Matthew Orahood
Author-email: morahood@gmail.com
Requires-Python: >=3.10,<4.0
Classifier: License :: Other/Proprietary License
Classifier: Programming Language :: Python :: 3
Classifier: Programming Language :: Python :: 3.10
Classifier: Programming Language :: Python :: 3.11
Classifier: Programming Language :: Python :: 3.12
Classifier: Programming Language :: Python :: 3.13
Requires-Dist: anthropic (>=0.45.2,<0.46.0)
Requires-Dist: apscheduler (>=3.11.0,<4.0.0)
Requires-Dist: openai (>=1.59.9,<2.0.0)
Requires-Dist: pydantic (>=2.10.3,<3.0.0)
Requires-Dist: requests (>=2.32.3,<3.0.0)
Requires-Dist: structlog (>=25.1.0,<26.0.0)
Project-URL: Documentation, https://docs.funcrunner.com
